setup.py
fill_broken_words/__init__.py
fill_broken_words/fill_broken_words.py
fill_broken_words/params_strs.py
fill_broken_words/possible_connection_suggests.py
fill_broken_words/sentence_process.py
fill_broken_words/utils.py
fill_broken_words.egg-info/PKG-INFO
fill_broken_words.egg-info/SOURCES.txt
fill_broken_words.egg-info/dependency_links.txt
fill_broken_words.egg-info/not-zip-safe
fill_broken_words.egg-info/requires.txt
fill_broken_words.egg-info/top_level.txt
fill_broken_words/patterns_vs_word/__init__.py
fill_broken_words/patterns_vs_word/group.py
fill_broken_words/patterns_vs_word/item.py