Metadata-Version: 1.1
Name: fill-broken-words
Version: 0.0.2
Summary: Fill broken words
Home-page: http://github.com/mvj3/fill_broken_words/
Author: David Chen
Author-email: mvjome@gmail.com
License: MIT
Platform: any
Classifier: Intended Audience :: Developers
Classifier: Operating System :: OS Independent
Classifier: Programming Language :: Python
Classifier: Topic :: Software Development :: Libraries :: Python Modules
